z3c/unconfigure/README.rst
z3c/unconfigure/__init__.py
z3c/unconfigure/config.py
z3c/unconfigure/meta.zcml
z3c/unconfigure/testing.py
z3c/unconfigure/tests/__init__.py
z3c/unconfigure/tests/overrides.rst
z3c/unconfigure/tests/subscribers.rst
z3c/unconfigure/tests/test_all.py
z3c/unconfigure/tests/fixtures/__init__.py
z3c/unconfigure/tests/fixtures/handlers.py
z3c/unconfigure/tests/fixtures/lolcat.zcml
z3c/unconfigure/tests/fixtures/overrides.zcml
z3c/unconfigure/tests/fixtures/overrides2.zcml
z3c_unconfigure-3.0.dist-info/LICENSE.txt
z3c_unconfigure-3.0.dist-info/METADATA
z3c_unconfigure-3.0.dist-info/WHEEL
z3c_unconfigure-3.0.dist-info/top_level.txt
z3c_unconfigure-3.0.dist-info/RECORD
