Metadata-Version: 2.2
Name: z3c.unconfigure
Version: 3.0
Summary: Disable specific ZCML directives in other package's configuration
Home-page: https://github.com/zopefoundation/z3c.unconfigure
Author: Philipp von Weitershausen
Author-email: zope-dev@zope.dev
License: ZPL
Classifier: Programming Language :: Python
Classifier: Intended Audience :: Developers
Classifier: License :: OSI Approved :: Zope Public License
Classifier: Programming Language :: Python
Classifier: Programming Language :: Python :: 3.9
Classifier: Programming Language :: Python :: 3.10
Classifier: Programming Language :: Python :: 3.11
Classifier: Programming Language :: Python :: 3.12
Classifier: Programming Language :: Python :: 3.13
Requires-Python: >=3.9
License-File: LICENSE.txt
Requires-Dist: setuptools
Requires-Dist: zope.configuration>=3.8.0
Requires-Dist: zope.component
Requires-Dist: zope.security
Requires-Dist: zope.event
Requires-Dist: zope.testing
Dynamic: author
Dynamic: author-email
Dynamic: classifier
Dynamic: description
Dynamic: home-page
Dynamic: license
Dynamic: requires-dist
Dynamic: requires-python
Dynamic: summary
